promptbeacon/__init__.py
promptbeacon/beacon.py
promptbeacon/py.typed
promptbeacon/analysis/__init__.py
promptbeacon/analysis/explainer.py
promptbeacon/analysis/scorer.py
promptbeacon/analysis/statistics.py
promptbeacon/cli/__init__.py
promptbeacon/cli/main.py
promptbeacon/core/__init__.py
promptbeacon/core/config.py
promptbeacon/core/exceptions.py
promptbeacon/core/schemas.py
promptbeacon/extraction/__init__.py
promptbeacon/extraction/mentions.py
promptbeacon/extraction/ranking.py
promptbeacon/extraction/sentiment.py
promptbeacon/providers/__init__.py
promptbeacon/providers/base.py
promptbeacon/providers/litellm_client.py
promptbeacon/reporting/__init__.py
promptbeacon/reporting/formats.py
promptbeacon/reporting/report.py
promptbeacon/storage/__init__.py
promptbeacon/storage/database.py
promptbeacon/storage/models.py
promptbeacon/storage/queries.py
promptbeacon-0.1.0.dist-info/METADATA
promptbeacon-0.1.0.dist-info/WHEEL
promptbeacon-0.1.0.dist-info/entry_points.txt
promptbeacon-0.1.0.dist-info/licenses/LICENSE
promptbeacon-0.1.0.dist-info/RECORD
