Metadata-Version: 2.4
Name: promptbeacon
Version: 0.1.0
Summary: LLM visibility monitoring for brands - track how your brand appears in AI-generated responses
Project-URL: Homepage, https://github.com/yotambraun/promptbeacon
Project-URL: Documentation, https://github.com/yotambraun/promptbeacon/tree/main/docs
Project-URL: Repository, https://github.com/yotambraun/promptbeacon
Project-URL: Changelog, https://github.com/yotambraun/promptbeacon/blob/main/CHANGELOG.md
Project-URL: Issues, https://github.com/yotambraun/promptbeacon/issues
Author: Yotam Braun
Maintainer: Yotam Braun
License-Expression: MIT
License-File: LICENSE
Keywords: ai,analytics,brand,brand-monitoring,chatgpt,claude,gemini,llm,monitoring,seo,visibility
Classifier: Development Status :: 4 - Beta
Classifier: Intended Audience :: Developers
Classifier: License :: OSI Approved :: MIT License
Classifier: Operating System :: OS Independent
Classifier: Programming Language :: Python :: 3
Classifier: Programming Language :: Python :: 3.10
Classifier: Programming Language :: Python :: 3.11
Classifier: Programming Language :: Python :: 3.12
Classifier: Programming Language :: Python :: 3.13
Classifier: Topic :: Internet :: WWW/HTTP :: Indexing/Search
Classifier: Topic :: Scientific/Engineering :: Artificial Intelligence
Classifier: Typing :: Typed
Requires-Python: >=3.10
Requires-Dist: duckdb<2.0.0,>=0.10.0
Requires-Dist: httpx<1.0.0,>=0.26.0
Requires-Dist: instructor<2.0.0,>=0.4.0
Requires-Dist: litellm<2.0.0,>=1.0.0
Requires-Dist: pydantic<3.0.0,>=2.0.0
Requires-Dist: python-dotenv<2.0.0,>=1.0.0
Requires-Dist: rich<14.0.0,>=13.0.0
Requires-Dist: typer<1.0.0,>=0.9.0
Provides-Extra: all
Requires-Dist: pandas>=2.0.0; extra == 'all'
Requires-Dist: rich<14.0.0,>=13.0.0; extra == 'all'
Requires-Dist: typer<1.0.0,>=0.9.0; extra == 'all'
Provides-Extra: cli
Requires-Dist: rich<14.0.0,>=13.0.0; extra == 'cli'
Requires-Dist: typer<1.0.0,>=0.9.0; extra == 'cli'
Provides-Extra: dev
Requires-Dist: mypy>=1.0.0; extra == 'dev'
Requires-Dist: pre-commit>=3.0.0; extra == 'dev'
Requires-Dist: pytest-asyncio>=0.21.0; extra == 'dev'
Requires-Dist: pytest-cov>=4.0.0; extra == 'dev'
Requires-Dist: pytest-mock>=3.0.0; extra == 'dev'
Requires-Dist: pytest>=7.0.0; extra == 'dev'
Requires-Dist: ruff>=0.1.0; extra == 'dev'
Requires-Dist: types-requests>=2.31.0; extra == 'dev'
Provides-Extra: pandas
Requires-Dist: pandas>=2.0.0; extra == 'pandas'
